setup.py
xswitch/__init__.py
xswitch/x_rsa.py
xswitch/xswitch.py
xswitch.egg-info/PKG-INFO
xswitch.egg-info/SOURCES.txt
xswitch.egg-info/dependency_links.txt
xswitch.egg-info/entry_points.txt
xswitch.egg-info/top_level.txt