Metadata-Version: 1.2
Name: xswitch
Version: 1.0.3
Summary: My usefull functions
Home-page: https://0xswitch.fr
Author: switch
Author-email: UNKNOWN
License: WTFPL
Platform: UNKNOWN
Requires-Python: >=2.7
